odoo/addons/disable_odoo_online/README.rst
odoo/addons/disable_odoo_online/__init__.py
odoo/addons/disable_odoo_online/__manifest__.py
odoo/addons/disable_odoo_online/i18n/de.po
odoo/addons/disable_odoo_online/i18n/disable_odoo_online.pot
odoo/addons/disable_odoo_online/i18n/es.po
odoo/addons/disable_odoo_online/i18n/fr.po
odoo/addons/disable_odoo_online/i18n/hr.po
odoo/addons/disable_odoo_online/i18n/hr_HR.po
odoo/addons/disable_odoo_online/i18n/it.po
odoo/addons/disable_odoo_online/i18n/nl_NL.po
odoo/addons/disable_odoo_online/i18n/pt_BR.po
odoo/addons/disable_odoo_online/i18n/sl.po
odoo/addons/disable_odoo_online/models/__init__.py
odoo/addons/disable_odoo_online/models/publisher_warranty_contract.py
odoo/addons/disable_odoo_online/readme/CONTRIBUTORS.rst
odoo/addons/disable_odoo_online/readme/DESCRIPTION.rst
odoo/addons/disable_odoo_online/static/description/icon.png
odoo/addons/disable_odoo_online/static/description/index.html
odoo/addons/disable_odoo_online/static/src/xml/base.xml
odoo/addons/disable_odoo_online/views/ir_ui_menu.xml
odoo14_addon_disable_odoo_online-14.0.1.0.1.dev6.dist-info/METADATA
odoo14_addon_disable_odoo_online-14.0.1.0.1.dev6.dist-info/WHEEL
odoo14_addon_disable_odoo_online-14.0.1.0.1.dev6.dist-info/top_level.txt
odoo14_addon_disable_odoo_online-14.0.1.0.1.dev6.dist-info/RECORD
